pyairctrl/__init__.py
pyairctrl/airctrl.py
pyairctrl/cloudctrl.py
pyairctrl/coap_air_client.py
pyairctrl/coap_client.py
pyairctrl/http_air_client.py
pyairctrl/http_client.py
pyairctrl/plain_coap_client.py
pyairctrl/status_transformer.py
pyairctrl/v_107_client.py
py_air_control-2.3.0.dist-info/LICENSE
py_air_control-2.3.0.dist-info/METADATA
py_air_control-2.3.0.dist-info/WHEEL
py_air_control-2.3.0.dist-info/entry_points.txt
py_air_control-2.3.0.dist-info/top_level.txt
py_air_control-2.3.0.dist-info/RECORD
