Metadata-Version: 2.1
Name: py-air-control
Version: 2.3.0
Summary: Command line program for controlling Philips air purifiers
Home-page: https://github.com/rgerganov/py-air-control
Author: Radoslav Gerganov
Author-email: rgerganov@gmail.com
License: UNKNOWN
Platform: UNKNOWN
Classifier: Programming Language :: Python :: 3
Classifier: License :: OSI Approved :: MIT License
Classifier: Operating System :: OS Independent
License-File: LICENSE
Requires-Dist: pycryptodomex (>=3.4.7)
Requires-Dist: CoAPthon3 (>=1.0.1)
